flask_s3_viewer/__init__.py
flask_s3_viewer/cli.py
flask_s3_viewer/config.py
flask_s3_viewer/errors.py
flask_s3_viewer/routers.py
flask_s3_viewer/aws/__init__.py
flask_s3_viewer/aws/cache.py
flask_s3_viewer/aws/ref.py
flask_s3_viewer/aws/s3.py
flask_s3_viewer/aws/session.py
flask_s3_viewer/blueprints/view.py
flask_s3_viewer/blueprints/static/js/flask.s3viewer.core.js
flask_s3_viewer/blueprints/templates/base/contents.html
flask_s3_viewer/blueprints/templates/base/controller.html
flask_s3_viewer/blueprints/templates/base/error.html
flask_s3_viewer/blueprints/templates/base/files.html
flask_s3_viewer/blueprints/templates/base/layout.html
flask_s3_viewer/blueprints/templates/base/prefixes.html
flask_s3_viewer/blueprints/templates/mdl/LICENSE
flask_s3_viewer/blueprints/templates/mdl/NOTICE
flask_s3_viewer/blueprints/templates/mdl/contents.html
flask_s3_viewer/blueprints/templates/mdl/controller.html
flask_s3_viewer/blueprints/templates/mdl/error.html
flask_s3_viewer/blueprints/templates/mdl/files.html
flask_s3_viewer/blueprints/templates/mdl/layout.html
flask_s3_viewer/blueprints/templates/mdl/prefixes.html
flask_s3_viewer-0.3.1.dist-info/LICENSE
flask_s3_viewer-0.3.1.dist-info/METADATA
flask_s3_viewer-0.3.1.dist-info/NOTICE
flask_s3_viewer-0.3.1.dist-info/WHEEL
flask_s3_viewer-0.3.1.dist-info/entry_points.txt
flask_s3_viewer-0.3.1.dist-info/top_level.txt
flask_s3_viewer-0.3.1.dist-info/RECORD
