Metadata-Version: 2.1
Name: flask_s3_viewer
Version: 0.3.1
Summary: Flask S3 Viewer is a powerful extension that makes it easy to browse S3 in any Flask application.
Home-page: https://github.com/hidekuma/flask-s3-viewer
Download-URL: https://github.com/hidekuma/flask-s3-viewer/releases
Author: Hidekuma
Author-email: d.hidekuma@gmail.com
Keywords: aws,s3,file,upload,flask,python,python3,browsing,uploader
Requires-Python: >= 3.10
License-File: LICENSE
License-File: NOTICE
Requires-Dist: boto3 >=1.28.22
Requires-Dist: flask >=2.0.0
